damage_chart_component/__init__.py
damage_chart_component/example.py
damage_chart_component/frontend/build/asset-manifest.json
damage_chart_component/frontend/build/bootstrap.min.css
damage_chart_component/frontend/build/bootstrap.min.css.map
damage_chart_component/frontend/build/index.html
damage_chart_component/frontend/build/static/css/main.328f3c68.css
damage_chart_component/frontend/build/static/css/main.328f3c68.css.map
damage_chart_component/frontend/build/static/js/main.4652cfee.js
damage_chart_component/frontend/build/static/js/main.4652cfee.js.LICENSE.txt
damage_chart_component/frontend/build/static/js/main.4652cfee.js.map
image_object_component-0.0.1.dist-info/LICENSE
image_object_component-0.0.1.dist-info/METADATA
image_object_component-0.0.1.dist-info/WHEEL
image_object_component-0.0.1.dist-info/top_level.txt
image_object_component-0.0.1.dist-info/RECORD
